.coveragerc
Changes
LICENSE
MANIFEST.in
README.rst
setup.py
Mopidy_Podcast_gpodder.net.egg-info/PKG-INFO
Mopidy_Podcast_gpodder.net.egg-info/SOURCES.txt
Mopidy_Podcast_gpodder.net.egg-info/dependency_links.txt
Mopidy_Podcast_gpodder.net.egg-info/entry_points.txt
Mopidy_Podcast_gpodder.net.egg-info/not-zip-safe
Mopidy_Podcast_gpodder.net.egg-info/requires.txt
Mopidy_Podcast_gpodder.net.egg-info/top_level.txt
mopidy_podcast_gpodder/__init__.py
mopidy_podcast_gpodder/directory.py
mopidy_podcast_gpodder/ext.conf
tests/__init__.py
tests/test_extension.py