Metadata-Version: 1.1
Name: Mopidy-Podcast-gpodder.net
Version: 0.1.0
Summary: Mopidy-Podcast extension for searching and browsing podcasts on gpodder.net
Home-page: https://github.com/tkem/mopidy-podcast-gpodder
Author: Thomas Kemmer
Author-email: tkemmer@computer.org
License: Apache License, Version 2.0
Platform: UNKNOWN
Classifier: Environment :: No Input/Output (Daemon)
Classifier: Intended Audience :: End Users/Desktop
Classifier: License :: OSI Approved :: Apache Software License
Classifier: Operating System :: OS Independent
Classifier: Programming Language :: Python :: 2
Classifier: Topic :: Multimedia :: Sound/Audio :: Players
